gdbfrontend/CODE_OF_CONDUCT.md
gdbfrontend/CONTRIBUTING.md
gdbfrontend/LICENSE
gdbfrontend/README.md
gdbfrontend/THIRDPARTYLICENSES
gdbfrontend/__main__.py
gdbfrontend/build_gdb.sh
gdbfrontend/commands.py
gdbfrontend/config.py
gdbfrontend/config.pyc
gdbfrontend/debug_events.py
gdbfrontend/debug_server.py
gdbfrontend/gdbfrontend
gdbfrontend/gdbfrontend-window
gdbfrontend/gdbfrontend.code-workspace
gdbfrontend/gdbfrontend.py
gdbfrontend/http_handler.py
gdbfrontend/http_server.py
gdbfrontend/plugin.py
gdbfrontend/run.py
gdbfrontend/run_gui.py
gdbfrontend/settings.py
gdbfrontend/setup.py
gdbfrontend/statics.py
gdbfrontend/terminal_daemon.py
gdbfrontend/tmux.conf
gdbfrontend/urls.py
gdbfrontend/util.py
gdbfrontend/websocket.py
gdbfrontend/__pycache__/commands.cpython-39.pyc
gdbfrontend/__pycache__/config.cpython-39.pyc
gdbfrontend/__pycache__/debug_events.cpython-39.pyc
gdbfrontend/__pycache__/debug_server.cpython-39.pyc
gdbfrontend/__pycache__/gdbfrontend.cpython-39.pyc
gdbfrontend/__pycache__/http_handler.cpython-39.pyc
gdbfrontend/__pycache__/http_server.cpython-39.pyc
gdbfrontend/__pycache__/plugin.cpython-39.pyc
gdbfrontend/__pycache__/settings.cpython-39.pyc
gdbfrontend/__pycache__/statics.cpython-39.pyc
gdbfrontend/__pycache__/terminal_daemon.cpython-39.pyc
gdbfrontend/__pycache__/urls.cpython-39.pyc
gdbfrontend/__pycache__/util.cpython-39.pyc
gdbfrontend/__pycache__/websocket.cpython-39.pyc
gdbfrontend/api/__init__.py
gdbfrontend/api/collabration.py
gdbfrontend/api/debug.py
gdbfrontend/api/flags.py
gdbfrontend/api/globalvars.py
gdbfrontend/api/process.py
gdbfrontend/api/url.py
gdbfrontend/api/__pycache__/__init__.cpython-37.pyc
gdbfrontend/api/__pycache__/__init__.cpython-38.pyc
gdbfrontend/api/__pycache__/__init__.cpython-39.pyc
gdbfrontend/api/__pycache__/collabration.cpython-37.pyc
gdbfrontend/api/__pycache__/collabration.cpython-39.pyc
gdbfrontend/api/__pycache__/debug.cpython-37.pyc
gdbfrontend/api/__pycache__/debug.cpython-38.pyc
gdbfrontend-0.11.3.dist-info/LICENSE
gdbfrontend-0.11.3.dist-info/METADATA
gdbfrontend-0.11.3.dist-info/WHEEL
gdbfrontend-0.11.3.dist-info/top_level.txt
gdbfrontend-0.11.3.dist-info/RECORD
