Metadata-Version: 2.1
Name: gdbfrontend
Version: 0.11.3
Summary: GDBFrontend is a easy, flexible and extensionable gui debugger.
Home-page: https://github.com/rohanrhu/gdb-frontend
Author: Oğuzhan Eroğlu
Author-email: rohanrhu2@gmail.com
License: UNKNOWN
Platform: UNKNOWN
Classifier: Development Status :: 4 - Beta
Classifier: Programming Language :: Python :: 3
Classifier: License :: OSI Approved :: GNU General Public License v3 (GPLv3)
Classifier: Operating System :: POSIX
Classifier: Operating System :: POSIX :: Linux
Classifier: Operating System :: Unix
Classifier: Programming Language :: C
Classifier: Programming Language :: C++
Classifier: Topic :: Software Development
Classifier: Topic :: Software Development :: Debuggers
Classifier: Topic :: Software Development :: Disassemblers
Classifier: Topic :: Software Development :: Testing
Requires-Python: >=3.6
